slypi/__init__.py
slypi/darray.py
slypi/pandas_util.py
slypi/cca/__init__.py
slypi/cca/upload_csv.py
slypi/cca/upload_dakota.py
slypi/cca/upload_hdf5.py
slypi/cca/upload_random.py
slypi/dac/__init__.py
slypi/dac/defaults.py
slypi/dac/run_chart.py
slypi/dac/tdms.py
slypi/dac/tdms_batches.py
slypi/dac/tdms_from_file.py
slypi/dac/tdms_util.py
slypi/dac/upload_gen.py
slypi/ensemble/__init__.py
slypi/ensemble/convert.py
slypi/ensemble/reduce.py
slypi/ensemble/table.py
slypi/ensemble/utilities.py
slypi/ensemble/algorithms/__init__.py
slypi/ensemble/algorithms/ai.py
slypi/ensemble/algorithms/reduction.py
slypi/ensemble/plugins/__init__.py
slypi/ensemble/plugins/convert.py
slypi/ensemble/plugins/generic.py
slypi/ensemble/plugins/ps.py
slypi/ensemble/plugins/vs.py
slypi/ps/__init__.py
slypi/ps/upload_csv.py
slypi/ps/upload_dakota.py
slypi/ps/upload_hdf5.py
slypi/util/__init__.py
slypi/util/get_model.py
slypi/util/get_project.py
slypi/util/list_markings.py
slypi/util/list_projects.py
slypi/vs/__init__.py
slypi/vs/upload_local.py
slypi/vs/vs_parse_files.py
slypi-1.2.0.dist-info/licenses/LICENSE
slypi-1.2.0.dist-info/METADATA
slypi-1.2.0.dist-info/WHEEL
slypi-1.2.0.dist-info/entry_points.txt
slypi-1.2.0.dist-info/top_level.txt
slypi-1.2.0.dist-info/RECORD
