Metadata-Version: 2.4
Name: slypi
Version: 1.2.0
Summary: Slycat python interface.
Author: Shawn martin
Author-email: smartin@sandia.gov
Project-URL: repository, https://github.com/sandialabs/slypi
Project-URL: documentation, https://slypi.readthedocs.io/en/latest/
Classifier: Programming Language :: Python :: 3
Requires-Python: <3.14,>=3.0
License-File: LICENSE
Requires-Dist: requests
Requires-Dist: requests-kerberos
Requires-Dist: numpy
Requires-Dist: scikit-learn
Requires-Dist: pandas
Requires-Dist: meshio
Requires-Dist: imageio[ffmpeg]
Requires-Dist: matplotlib
Requires-Dist: ipyparallel
Requires-Dist: cloudpickle
Requires-Dist: umap-learn
Requires-Dist: pyarrow
Provides-Extra: auto
Requires-Dist: pymks; extra == "auto"
Provides-Extra: tdms
Requires-Dist: npTDMS; extra == "tdms"
Requires-Dist: natsort; extra == "tdms"
Dynamic: license-file
